wn/__init__.py
wn/__main__.py
wn/_add.py
wn/_config.py
wn/_core.py
wn/_db.py
wn/_download.py
wn/_exceptions.py
wn/_export.py
wn/_lexicon.py
wn/_metadata.py
wn/_module_functions.py
wn/_queries.py
wn/_types.py
wn/_util.py
wn/_wordnet.py
wn/constants.py
wn/ic.py
wn/ili.py
wn/index.toml
wn/lmf.py
wn/metrics.py
wn/morphy.py
wn/project.py
wn/py.typed
wn/schema.sql
wn/similarity.py
wn/taxonomy.py
wn/util.py
wn/validate.py
wn/compat/__init__.py
wn/compat/sensekey.py
wn-1.0.0.dist-info/METADATA
wn-1.0.0.dist-info/WHEEL
wn-1.0.0.dist-info/licenses/LICENSE
wn-1.0.0.dist-info/RECORD
