Metadata-Version: 2.4
Name: wn
Version: 1.0.0
Summary: Wordnet interface library
Project-URL: homepage, https://github.com/goodmami/wn
Project-URL: documentation, https://wn.readthedocs.io
Project-URL: changelog, https://github.com/goodmami/wn/blob/main/CHANGELOG.md
Author-email: Michael Wayne Goodman <goodman.m.w@gmail.com>
License: MIT License
License-File: LICENSE
Keywords: interlingual,language,library,linguistics,wordnet
Classifier: Development Status :: 4 - Beta
Classifier: Environment :: Console
Classifier: Intended Audience :: Developers
Classifier: Intended Audience :: Information Technology
Classifier: Intended Audience :: Science/Research
Classifier: License :: OSI Approved :: MIT License
Classifier: Programming Language :: Python :: 3
Classifier: Programming Language :: Python :: 3.10
Classifier: Programming Language :: Python :: 3.11
Classifier: Programming Language :: Python :: 3.12
Classifier: Programming Language :: Python :: 3.13
Classifier: Programming Language :: Python :: 3.14
Classifier: Topic :: Scientific/Engineering :: Information Analysis
Classifier: Topic :: Software Development :: Libraries :: Python Modules
Classifier: Topic :: Text Processing :: Linguistic
Requires-Python: >=3.10
Requires-Dist: httpx
Requires-Dist: tomli; python_version < '3.11'
Provides-Extra: editor
Requires-Dist: wn-editor; extra == 'editor'
